frontend/__init__.py
frontend/app.py
frontend/utils.py
xpotato/__init__.py
xpotato/dataset/__init__.py
xpotato/dataset/dataset.py
xpotato/dataset/explainable_dataset.py
xpotato/dataset/explainable_sample.py
xpotato/dataset/relation_dataset.py
xpotato/dataset/relation_sample.py
xpotato/dataset/sample.py
xpotato/dataset/utils.py
xpotato/features/__init__.py
xpotato/features/utils.py
xpotato/graph_extractor/__init__.py
xpotato/graph_extractor/extract.py
xpotato/graph_extractor/graph.py
xpotato/graph_extractor/rule.py
xpotato/models/__init__.py
xpotato/models/model.py
xpotato/models/trainer.py
xpotato/models/utils.py
xpotato-0.1.5.dist-info/LICENSE
xpotato-0.1.5.dist-info/METADATA
xpotato-0.1.5.dist-info/WHEEL
xpotato-0.1.5.dist-info/top_level.txt
xpotato-0.1.5.dist-info/RECORD
