Metadata-Version: 2.1
Name: xpotato
Version: 0.1.5
Summary: XAI human-in-the-loop information extraction framework
Home-page: https://github.com/adaamko/POTATO
Author: Adam Kovacs, Gabor Recski
Author-email: adam.kovacs@tuwien.ac.at, gabor.recski@tuwien.ac.at
License: MIT
Platform: UNKNOWN
Classifier: Development Status :: 3 - Alpha
Classifier: Intended Audience :: Developers
Classifier: Intended Audience :: Education
Classifier: Intended Audience :: Science/Research
Classifier: License :: OSI Approved :: MIT License
Classifier: Operating System :: OS Independent
Classifier: Programming Language :: Python :: 3
Classifier: Programming Language :: Python :: 3.9
Classifier: Topic :: Scientific/Engineering :: Artificial Intelligence
License-File: LICENSE
Requires-Dist: pandas (>=1.3.5)
Requires-Dist: tqdm
Requires-Dist: stanza (==1.3.0)
Requires-Dist: scikit-learn (==1.0.2)
Requires-Dist: eli5 (==0.11.0)
Requires-Dist: jinja2 (==3.0.1)
Requires-Dist: graphviz (==0.18.2)
Requires-Dist: penman (>=1.2.1)
Requires-Dist: networkx (==2.6.3)
Requires-Dist: rank-bm25 (==0.2.1)
Requires-Dist: streamlit (==1.15.0)
Requires-Dist: streamlit-aggrid (==0.2.3.post2)
Requires-Dist: scikit-criteria (==0.5)
Requires-Dist: tuw-nlp (==0.1.0)
Requires-Dist: amrlib (==0.6.0)
Requires-Dist: protobuf (==3.20.0)
Requires-Dist: pytest (>=7.1.3)
Requires-Dist: fastapi
Requires-Dist: uvicorn[standard]
